{
  "doc_id": "262ee7aef0cd358a",
  "url": "http://www.hbets.cn/view_335.html",
  "title": "湖北省产品碳足迹公共服务平台正式发布",
  "content": "2月7日，我中心2018年第一次股东会、第二届董事会第一次会议、第二届监事会第一次会议在中心报告厅分别召开。会议由陈志祥董事长主持，武汉光谷联合产权交易所、中国水利电力物资集团有限公司、神雾环保技术股份有限公司、湖北省宏泰国有资本投资运营集团有限公司、湖北省农业生产资料控股集团有限公司、国电长源电力股份有限公司、中国建材检验认证集团股份有限公司、武汉钢铁（集团）公司、大冶有色金属集团控股有限公司等9家股东单位代表及董事、监事参加了会议。 股东代表、董事充分肯定了中心在2017年全国碳市场建设中取得的成绩，充分赞同中心下步业务发展规划，股东单位表示，今后将继续全力支持中心服务全国碳市场建设，为建成两个中心创造有利条件。",
  "section": "Center_Dynamics",
  "publish_date": "2018-02-07T00:00:00",
  "view_count": 8825,
  "content_length": 312,
  "content_hash": "5f05e3fb4e5202b5d5352bf4b6ef3dec",
  "scraped_at": "2025-08-09T07:18:58.932201",
  "source": "HBETS",
  "source_name_cn": "Hubei Carbon Emission Trading Center",
  "source_name_en": "Hubei Emission Trading Scheme"
}