{
  "doc_id": "9905a672ab6758f1",
  "url": "http://www.hbets.cn/view_1616.html",
  "title": "关于举办温室气体管理师基础知识课程培训的通知",
  "content": "12月4日，湖北碳交中心举办聚绿成金碳话未来系列会员沙龙第一期活动。来自全国25家会员机构的43名代表参会。湖北碳交中心党委副书记、总经理何昌福，党委委员、副总经理张雁出席本次活动。 活动邀请华源电力设计院、湖北永业行评估咨询有限公司、武汉华商低碳能源股份有限公司、武汉本物科技股份有限公司等会员机构代表，就自身业务发展情况、参与湖北碳市场经历及未来合作方向等方面进行了交流发言。湖北碳交中心相关部门业务骨干分别对《湖北省2022年度碳排放权配额分配方案》《武汉市碳普惠方法学试行》《湖北省绿色融资企业评价指南试行》《温室气体自愿减排项目方法学》等最新政策文件进行解读，并与现场会员机构代表开展互动交流。活动还邀请外部专家就ESG投资管理进行分享交流。 本次活动采取线上线下相结合的方式，取得了良好效果，获得会员机构一致好评。湖北碳交中心将以本次活动为开端，定期举办内容丰富、形式多样的系列会员沙龙活动，为会员机构提供专业优质的服务。",
  "section": "Center_Dynamics",
  "publish_date": "2023-12-06T00:00:00",
  "view_count": 1293,
  "content_length": 417,
  "content_hash": "c050661eeab144e36e782085ed0d8af7",
  "scraped_at": "2025-08-09T07:17:33.264718",
  "source": "HBETS",
  "source_name_cn": "Hubei Carbon Emission Trading Center",
  "source_name_en": "Hubei Emission Trading Scheme"
}