{
  "doc_id": "beb7be8842f2d886",
  "url": "http://www.hbets.cn/view_1223.html",
  "title": "湖北碳交助力湖北省首家政策性银行实现碳中和",
  "content": "4月7日上午，中国民用机场协会理事长、双碳机场评价工作委员会主任王瑞萍到访湖北碳交中心，湖北宏泰集团党委委员、副总经理、湖北碳交中心党委书记、董事长吴玉祥，中碳登党委委员、副总经理汪令新，湖北碳交中心党委副书记、总经理何昌福一同接待了王瑞萍一行。 在调研会上，吴玉祥对王瑞萍一行的到来表示欢迎，并介绍了湖北宏泰集团及碳市场建设相关情况。他表示，湖北宏泰集团已形成完整的双碳体系化服务架构，希望未来与中国民用机场协会加强合作，发挥双方合力，服务机场协会会员单位绿色低碳发展。随后，何昌福介绍了湖北碳交中心发展情况及湖北碳市场建设情况。汪令新介绍了中碳登建设及发展相关情况。 王瑞萍对湖北宏泰集团在试点和全国两个碳市场建设取得的成绩表示充分肯定，并详细介绍了中国民用机场协会在双碳领域开展的工作。她表示，宏泰集团在碳市场建设运营方面经验丰富，希望依托宏泰集团的先进经验和完善的服务体系，开展全面务实合作，共同推进机场协会会员单位双碳工作，助力全国实现双碳目标。",
  "section": "Center_Dynamics",
  "publish_date": "2025-07-02T00:00:00",
  "view_count": null,
  "content_length": 428,
  "content_hash": "43cebb3812bb1ff2018f306b6476799e",
  "scraped_at": "2025-08-08T22:46:32.470111",
  "source": "HBETS",
  "source_name_cn": "Hubei Carbon Emission Trading Center",
  "source_name_en": "Hubei Emission Trading Scheme"
}