{
  "doc_id": "f55ad6349d6114f8",
  "url": "http://www.hbets.cn/view_748.html",
  "title": "湖北碳交助力湖北省首家政策性银行实现碳中和",
  "content": "1月14日，湖北碳排放权交易中心与湖北大学达成战略合作协议，共同致力于国家重点研发计划课题和气候智慧型农业研究。武汉光谷联合产权交易所党委书记、董事长兼碳交中心董事长曾庆祝，湖北大学党委副书记、校长刘建平代表双方签字并致辞。 曾庆祝董事长于会上表示，为贯彻落实习近平总书记关于碳达峰、碳中和的重要指示精神，推动湖北经济高质量发展，湖北碳排放权交易中心与湖北大学本着资源共享、优势互补的原则，共建湖北大学中国农业碳减排碳交易研究中心。对于碳交中心来说，今天与在双碳技术研发和创新方面具有雄厚基础的湖北大学合作，不只是起点，更是延续、是升级，是进一步加强合作。双方将以此为契机，在人才培养、科学研究、产业应用、智力支持等方面深入交流。 湖北省生态环境厅二级巡视员田啟，湖北省科技厅社发处处长史红，华中科技大学煤燃烧国家重点实验室副主任、教授赵海波，湖北大学党委常委、副校长艾青松，湖北碳排放权交易中心副总经理杨光星以及湖北大学人文社科研究院、湖北大学科学技术发展研究院、湖北大学商学院等师生代表参加了签约仪式。",
  "section": "Center_Dynamics",
  "publish_date": "2025-07-02T00:00:00",
  "view_count": null,
  "content_length": 453,
  "content_hash": "3c3033c408341ebfcf409b6108c89245",
  "scraped_at": "2025-08-08T22:48:01.555852",
  "source": "HBETS",
  "source_name_cn": "Hubei Carbon Emission Trading Center",
  "source_name_en": "Hubei Emission Trading Scheme"
}