{
  "doc_id": "f6515f2e73600f6b",
  "url": "http://www.hbets.cn/view_2501.html",
  "title": "湖北省产品碳足迹公共服务平台正式发布",
  "content": "为深入贯彻落实中央八项规定精神，坚决整治违规吃喝，6月16日上午，湖北碳交中心党委书记、董事长张选强主持召开2025年警示教育大会暨党委理论学习中心组第7次（扩大）学习，并以《严守八项规定红线 筑牢碳交清风根基》为题讲专题党课。会议通过集中学习、案例警示、签署承诺、党课教育等形式，强化了纪律约束，为中心高质量转型发展提供坚实保障。中心党委班子成员、全体党员干部及重点岗位人员参会。 会议传达学习了中央层面深入贯彻中央八项规定精神学习教育工作专班、中央纪委办公厅关于2起党员干部在学习教育期间违规吃喝、严重违反中央八项规定精神典型问题的通报，传达学习省委常委会、全省集中整治违规吃喝动员部署会精神。下属平台公司负责人结合个人思想和工作实际作交流发言。全体党员干部集中观看警示教育片《贪路无归碳路自毁》，签署《湖北宏泰集团党员干部员工自觉遵守中央八项规定精神承诺书》。中心党委委员、纪委书记聂茗通报中心专项检查情况。 会议指出，一是要以政治三力校准思想坐标，深刻认识整治工作的紧迫性。全体党员干部要深刻认识到整治违规吃喝是党中央推进全面从严治党的重要抓手，是省委净化政治生态的具体行动，更是中心高质量发展的纪律保障。二是要以全链治理压实责任链条，构建常态长效的整治机制。要坚持当下改与长久立相结合，抓好重点环节。自查自纠要见底，监督执纪要从严，制度建设要闭环。三是要以头雁效应引领作风转变，凝聚担当作为的发展合力。领导班子成员要做到三个带头。全体党员干部要把整治成效转化为干事动能，在碳市场建设、绿色金融创新、碳普惠探索等重点工作中，以严真细实快的作风攻坚克难，坚决杜绝吃喝歪风侵蚀干事创业的精气神。 会议要求，全体党员干部要以本次会议为契机，压紧压实政治责任，刀刃向内革除积弊，真抓实干树正新风，从严从实抓好深入贯彻中央八项规定精神学习教育，锻造一支清廉干净的人才队伍，为推动湖北碳交中心高质量转型发展保驾护航！",
  "section": "Center_Dynamics",
  "publish_date": "2025-06-16T00:00:00",
  "view_count": 339,
  "content_length": 806,
  "content_hash": "3e6058dd28a7070ccd9626c58e68183f",
  "scraped_at": "2025-08-09T07:16:26.469140",
  "source": "HBETS",
  "source_name_cn": "Hubei Carbon Emission Trading Center",
  "source_name_en": "Hubei Emission Trading Scheme"
}