{
  "doc_id": "f8b098e09e721840",
  "url": "http://www.hbets.cn/view_1609.html",
  "title": "关于举办温室气体管理师基础知识课程培训的通知",
  "content": "11月30日，武汉市生态环境局发布《武汉市分布式光伏发电项目运行碳普惠方法学试行》《武汉市规模化家禽粪污资源化利用碳普惠方法学试行》《武汉市基于电力需求响应的居民低碳用电碳普惠方法学试行》。首批方法学的发布为武汉市碳普惠减排项目或个人碳减排场景的核算核查提供了依据。 根据湖北省生态环境厅发布的《湖北省2022年度碳排放权配额分配方案》，武汉市辖区内纳入企业可以使用在武汉市碳普惠体系下由市生态环境局签发的碳普惠减排量抵销本企业2022年度实际减排量，1吨碳普惠减排量相当于1吨湖北碳配额。 分布式光伏项目运行方法学适用于武汉市行政区内机关、企事业单位、居民家庭运行分布式光伏发电设施，要求单点并网装机容量应小于6兆瓦。 家禽粪污资源化利用方法学适用于武汉行政区内的规模化家禽养殖场、以鸡粪为主要原料的畜禽粪污集中处理中心，要求蛋鸡养殖场规模在5万只以上，肉鸡养殖场规模在10万只以上。 居民低碳用电方法学针对的是个人低碳行为，其减排量的核算、核查和登记通过武碳江湖小程序和碳普惠登记平台在线完成，居民可实时通过武碳江湖查看个人碳账户中的碳普惠减排量数据。个人碳普惠减排量单位以克二氧化碳当量gCO2e计，累积至1吨后可入市交易。",
  "section": "Center_Dynamics",
  "publish_date": "2025-08-06T00:00:00",
  "view_count": null,
  "content_length": 515,
  "content_hash": "1b46ed33c89f9b20cbe6e71f9092921d",
  "scraped_at": "2025-08-08T22:45:15.831971",
  "source": "HBETS",
  "source_name_cn": "Hubei Carbon Emission Trading Center",
  "source_name_en": "Hubei Emission Trading Scheme"
}