{
  "doc_id": "1f9bfba9ef458839",
  "url": "https://www.cnemission.com/article/news/jysdt/202206/20220600002611.shtml",
  "title": "携手低碳生活，共建绿色家园青少年主题路演活动顺利举办",
  "content": "为深入学习宣传贯彻习近平生态文明思想，支持鼓励青少年学习了解应对气候变化、倡导低碳生活、参与节能减排和环保实践活动，不断提升青少年低碳节能意识，共建绿色家园，2022年6月25日上午，在第11届中国（广州）国际金融交易博览会绿色金融助力双碳展区由广州碳排放权交易中心（简称：广碳所）和广州金融发展服务中心（简称：广州金服）联合主办了携手低碳生活，共建绿色家园主题活动。本次活动由广碳所创新业务部总经理张辰进行开场致辞，表示应对气候变化、碳市场、绿色金融等不仅是政府、企业和机构的议题，青少年的聪明才智、远见卓识和低碳生活的点滴行动，更能推动我们在实现碳达峰碳中和目标的道路上不断前行。活动中5名广州市中小学生进行了低碳生活的主题演讲，他们声情并茂地展示了自己对于环境保护、低碳生活等的认识与理解，青少年们对低碳生活，共建美丽绿色家园的热情与向往感染了现场观众。广州金服总监李恺总结致辞中表示，青少年应积极主动承担起环境保护的责任，倡导低碳出行方式，通过力所能及的行动践行绿色环保理念，为应对气候变化贡献个人智慧与力量。随后，本次活动为5位同学颁发了由广碳所和广州金服共同出具的低碳之星证书。广州市地方金融监督管理局市管一级调研员王德昌等莅临指导并与同学们合影留念。此次主题路演活动鼓励广大青少年积极参与低碳环保行动，提高社会公众对绿色金融的认识。下一步，广碳所将继续推动绿色低碳发展，发挥绿色金融基础设施服务平台和绿色要素定价平台作用，为双碳目标的实现贡献市场化力量。",
  "section": "Center_Dynamics",
  "publish_date": "2022-06-25T00:00:00",
  "view_count": null,
  "content_length": 634,
  "content_hash": "11e9189fb5310492ef1d89f3931111d4",
  "scraped_at": "2025-08-09T08:00:27.515841",
  "source": "GZETS",
  "source_detail": "广州碳排放权交易中心",
  "source_name_cn": "广州碳排放权交易中心",
  "source_name_en": "Guangzhou Emission Trading Scheme"
}