{
  "doc_id": "66b2eb88cb092352",
  "url": "https://www.cnemission.com/article/news/jysdt/202209/20220900002700.shtml",
  "title": "推进能源低碳转型，广碳所支持山西双碳平台建设",
  "content": "来源： 时间： 来源： 时间： 9月1日，2022年太原能源低碳发展论坛在晋阳湖国际会议中心隆重开幕，国内外嘉宾齐聚一堂，聚焦能源转型，共话低碳发展。 本届太原论坛主题为能源 双碳 发展，为期三天，重点开展13N系列活动。组织一场开幕式暨高峰论坛；开展2022中国（太原）国际能源产业博览会、第十二届全球新能源企业500强峰会、签约活动等三场专题活动；组织13场分论坛，以及驻华使节圆桌会议、以色列主宾国活动等。3N系列活动和分论坛，聚焦氢能经济、碳汇和绿色金融、低碳技术应用、新型电力系统、地热能发展、煤层气高效利用等领域，深入开展高峰对话、前沿技术研讨、创新成果展示、重大信息发布等。 会上，广碳所与（德国）博众能源转型论坛、山西省能源研究会、中国能源建设集团有限公司、院士智谷和思源碳中和科技（山西）有限公司签订合作备忘录，共建山西双碳能源革命研究院，服务地方低碳转型，合力推动碳达峰、碳中和、能源革命和产业科技创新发展。广碳所与合作方签署合作备忘录山西双碳能源革命研究院揭牌仪式 文章正文 9 月 1 日， 2022 年太原能源低碳发展论坛在晋阳湖国际会议中心隆重开幕，国内外嘉宾齐聚一堂，聚焦能源转型，共话低碳发展。 本届太原论坛主题为能源 双碳 发展，为期三天，重点开展 13N 系列活动。组织一场开幕式暨高峰论坛；开展 2022 中国（太原）国际能源产业博览会、第十二届全球新能源企业 500 强峰会、签约活动等三场专题活动；组织 13 场分论坛，以及驻华使节圆桌会议、以色列主宾国活动等。 3N 系列活动和分论坛，聚焦氢能经济、碳汇和绿色金融、低碳技术应用、新型电力系统、地热能发展、煤层气高效利用等领域，深入开展高峰对话、前沿技术研讨、创新成果展示、重大信息发布等。 会上，广碳所与（德国）博众能源转型论坛、山西省能源研究会、中国能源建设集团有限公司、院士智谷和思源碳中和科技（山西）有限公司签订合作备忘录，共建山西双碳能源革命研究院，服务地方低碳转型，合力推动碳达峰、碳中和、能源革命和产业科技创新发展。 广碳所与合作方签署合作备忘录 山西双碳能源革命研究院揭牌仪式 新闻中心 交易中心公告 交易中心动态 省市动态 国内资讯 国际资讯 绿金委动态 新闻中心 交易中心公告 交易中心动态 省市动态 国内资讯 国际资讯 绿金委动态 地址：广州市花都区天贵路103号保利国际金融中心T4栋6楼 电话：02028875088 传真：02028875099 版权所有广州碳排放权交易中心有限公司 粤ICP备12094092号 粤公网安备 44011402000549号 网站安全检测平台 地址：广州市花都区天贵路103号保利国际金融中心T4栋6楼 电话：02028875088 传真：02028875099 版权所有广州碳排放权交易中心有限公司 粤ICP备12094092号 粤公网安备 44011402000549号 网站安全检测平台",
  "section": "Center_Dynamics",
  "publish_date": null,
  "view_count": null,
  "content_length": 1223,
  "content_hash": "4c6cbed89f1fb7f92d1677143bb56430",
  "scraped_at": "2025-08-09T01:01:48.035567",
  "source": "GZETS",
  "source_detail": "广州碳排放权交易中心",
  "source_name_cn": "广州碳排放权交易中心",
  "source_name_en": "Guangzhou Emission Trading Scheme"
}