{
  "doc_id": "f0879be9a95de41e",
  "url": "https://www.cnemission.com/article/news/jysdt/202305/20230500002950.shtml",
  "title": "广东省博物馆联合广碳所等开展绿色博物馆主题活动",
  "content": "[Limited text content available]",
  "section": "Center_Dynamics",
  "publish_date": null,
  "view_count": null,
  "content_length": 32,
  "content_hash": "d84117566097227e0565440d1f4142d4",
  "scraped_at": "2025-08-09T01:01:41.705693",
  "source": "GZETS",
  "source_detail": "广州碳排放权交易中心",
  "source_name_cn": "广州碳排放权交易中心",
  "source_name_en": "Guangzhou Emission Trading Scheme"
}