{
  "doc_id": "4971a0f48c56f922",
  "url": "https://www.mee.gov.cn/xxgk2018/xxgk/xxgk01/201808/t20180815_629604.html",
  "title": "关于发布《环境空气 氟化物的测定 滤膜采样氟离子选择电极法》等两项国家环境保护标准的公告",
  "content": "关于发布《环境空气 氟化物的测定 滤膜采样氟离子选择电极法》等两项国家环境保护标准的公告 为贯彻《中华人民共和国环境保护法》，保护生态环境，保障人体健康，规范生态环境监测工作，现批准《环境空气 氟化物的测定 滤膜采样氟离子选择电极法》等两项标准为国家环境保护标准，并予发布。 标准名称、编号如下： 一、《环境空气 氟化物的测定 滤膜采样氟离子选择电极法》（HJ955-2018）； 二、《环境空气 苯并a芘的测定 高效液相色谱法》（HJ956-2018）。 以上标准自2018年9月1日起实施，由中国环境出版社出版。标准内容可在生态环境部网站（kjsmeegovcnhjbhbz）查询。 特此公告。 生态环境部 2018年7月29日 抄送：各省、自治区、直辖市环境保护厅（局），新疆生产建设兵团环境保护局，环境标准研究所，各标准主编单位。 生态环境部办公厅2018年7月30日印发 字号：大中小打印仅打印内容",
  "section": "Notices",
  "publish_date": "2018-09-01T00:00:00",
  "doc_number": null,
  "content_length": 404,
  "content_hash": "cbe4efb72f27010abad07a98a610e9e8",
  "scraped_at": "2025-08-09T07:12:42.702857",
  "source": "MEE",
  "source_name_cn": "生态环境部",
  "source_name_en": "Ministry of Ecology and Environment"
}