{
  "doc_id": "7214d34bb6488092",
  "url": "https://www.mee.gov.cn/xxgk2018/xxgk/xxgk01/201811/t20181115_674010.html",
  "title": "关于发布国家环境保护标准《固定污染源废气 一氧化碳的测定 定电位电解法》的公告",
  "content": "为贯彻《中华人民共和国环境保护法》，保护生态环境，保障人体健康，规范生态环境监测工作，现批准《固定污染源废气 一氧化碳的测定定电位电解法》为国家环境保护标准，并予发布。 标准名称、编号如下： 《固定污染源废气一氧化碳的测定定电位电解法》（HJ973-2018）。 以上标准自2019年3月1日起实施，由中国环境出版社出版，标准内容可在生态环境部网站（kjsmeegovcnhjbhbz）查询。 特此公告。 生态环境部 2018年11月13日 抄送：各省、自治区、直辖市生态环境（环境保护）厅（局），新疆生产建设兵团环境保护局，环境标准研究所，各标准承担单位。 生态环境部办公厅2018年11月14日印发",
  "section": "Notices",
  "publish_date": "2019-03-01T00:00:00",
  "doc_number": null,
  "content_length": 301,
  "content_hash": "cd3fc168e051c987151b5425c81b9467",
  "scraped_at": "2025-08-09T07:12:38.286215",
  "source": "MEE",
  "source_name_cn": "生态环境部",
  "source_name_en": "Ministry of Ecology and Environment"
}