{
  "doc_id": "9ad5a443a8bc09f3",
  "url": "https://www.mee.gov.cn/xxgk2018/xxgk/xxgk01/201809/t20180917_644167.html",
  "title": "关于2018年第一季度主要污染物排放严重超标重点排污单位名单和处罚整改情况的公告",
  "content": "为加强污染源环境监管信息公开，促进地方政府履行生态环境保护监管职责，督促企业事业单位落实生态环境保护主体责任，按照《中华人民共和国环境保护法》《中华人民共和国政府信息公开条例》等法律法规和有关规定，我部根据污染源自动监测数据以及地方生态环境部门核实查处情况，汇总整理了2018年第一季度158家主要污染物排放严重超标重点排污单位名单和处罚整改情况，现予公告。 附件：2018年第一季度主要污染物排放严重超标重点排污单位名单和处罚整改情况 生态环境部 2018年9月3日 生态环境部办公厅2018年9月10日印发",
  "section": "Notices",
  "publish_date": "2018-09-03T00:00:00",
  "doc_number": null,
  "content_length": 255,
  "content_hash": "1d6d43ea419b1137694e7243ac623df4",
  "scraped_at": "2025-08-09T07:12:40.281715",
  "source": "MEE",
  "source_name_cn": "生态环境部",
  "source_name_en": "Ministry of Ecology and Environment"
}