{
  "doc_id": "c0ad9c058eed4133",
  "url": "https://www.cnemission.com/article/news/ssdt/201807/20180700001494.shtml",
  "title": "关于广东省2017年度碳排放配额履约工作的最新公告",
  "content": "来源： 时间： 来源： 时间： 根据《广东省碳排放管理试行办法》（广东省政府令第197号）规定，每年6月20日前，控排企业和单位应当根据上年度实际排放量，完成配额清缴工作，并由省发展改革委注销。2018年6月21日，我委对未按时履行配额清缴义务的1家企业发出责令改正通知书；6月28日，该企业在规定的整改期内完成配额清缴。至此，广东省246家控排企业和单位均已足额完成配额清缴义务，2017年度配额履约工作圆满收官。 文章正文 根据《广东省碳排放管理试行办法》（广东省政府令第 197 号）规定，每年 6 月 20 日前，控排企业和单位应当根据上年度实际排放量，完成配额清缴工作，并由省发展改革委注销。 2018 年 6 月 21 日，我委对未按时履行配额清缴义务的 1 家企业发出责令改正通知书； 6 月 28 日，该企业在规定的整改期内完成配额清缴。至此，广东省 246 家控排企业和单位均已足额完成配额清缴义务， 2017 年度配额履约工作圆满收官。 新闻中心 交易中心公告 交易中心动态 省市动态 国内资讯 国际资讯 绿金委动态 新闻中心 交易中心公告 交易中心动态 省市动态 国内资讯 国际资讯 绿金委动态 地址：广州市花都区天贵路103号保利国际金融中心T4栋6楼 电话：02028875088 传真：02028875099 版权所有广州碳排放权交易中心有限公司 粤ICP备12094092号 粤公网安备 44011402000549号 网站安全检测平台 地址：广州市花都区天贵路103号保利国际金融中心T4栋6楼 电话：02028875088 传真：02028875099 版权所有广州碳排放权交易中心有限公司 粤ICP备12094092号 粤公网安备 44011402000549号 网站安全检测平台",
  "section": "Provincial_Municipal",
  "publish_date": null,
  "view_count": null,
  "content_length": 758,
  "content_hash": "afcb6bce06116384bcc3a19b93197c30",
  "scraped_at": "2025-08-09T01:04:47.961490",
  "source": "GZETS",
  "source_detail": "广东省发展改革委",
  "source_name_cn": "广州碳排放权交易中心",
  "source_name_en": "Guangzhou Emission Trading Scheme"
}