[
  {
    "doc_id": "c08c800e2f36838c",
    "title": "MBAESG双驱商业领袖高级研修班招生简章",
    "source": "HBETS",
    "publish_date": "2013-11-08T00:00:00",
    "similarities": {
      "supply": {
        "major_decrease": 40,
        "minor_decrease": 30,
        "minor_increase": 20,
        "major_increase": 50
      },
      "demand": {
        "major_decrease": 40,
        "minor_decrease": 30,
        "minor_increase": 20,
        "major_increase": 50
      },
      "policy_strength": {
        "informational": 20,
        "encouraged": 60,
        "binding": 30,
        "mandatory": 10
      },
      "confidence": 40
    },
    "scores": {
      "supply": 3.57,
      "demand": 3.57,
      "policy_strength": 41.58,
      "confidence": 40,
      "interpretations": {
        "supply": "Neutral supply impact",
        "demand": "Neutral demand impact",
        "policy_strength": "Encouraged/voluntary policy",
        "overall": "Low confidence: neutral price impact with voluntary measures"
      }
    },
    "timestamp": "2025-08-11T05:04:49.049852"
  },
  {
    "doc_id": "62acdd178babcca1",
    "title": "MBAESG双驱商业领袖高级研修班招生简章",
    "source": "HBETS",
    "publish_date": "2013-03-11T00:00:00",
    "similarities": {
      "supply": {
        "major_decrease": 40,
        "minor_decrease": 30,
        "minor_increase": 20,
        "major_increase": 50
      },
      "demand": {
        "major_decrease": 40,
        "minor_decrease": 30,
        "minor_increase": 20,
        "major_increase": 50
      },
      "policy_strength": {
        "informational": 70,
        "encouraged": 60,
        "binding": 30,
        "mandatory": 20
      },
      "confidence": 50
    },
    "scores": {
      "supply": 3.57,
      "demand": 3.57,
      "policy_strength": 33.28,
      "confidence": 50,
      "interpretations": {
        "supply": "Neutral supply impact",
        "demand": "Neutral demand impact",
        "policy_strength": "Encouraged/voluntary policy",
        "overall": "Low confidence: neutral price impact with voluntary measures"
      }
    },
    "timestamp": "2025-08-11T05:04:49.107991"
  },
  {
    "doc_id": "b2523cc2b0a3728f",
    "title": "湖北碳交助力湖北省首家政策性银行实现碳中和",
    "source": "HBETS",
    "publish_date": "2013-11-01T00:00:00",
    "similarities": {
      "supply": {
        "major_decrease": 20,
        "minor_decrease": 15,
        "minor_increase": 10,
        "major_increase": 25
      },
      "demand": {
        "major_decrease": 20,
        "minor_decrease": 15,
        "minor_increase": 10,
        "major_increase": 25
      },
      "policy_strength": {
        "informational": 30,
        "encouraged": 40,
        "binding": 10,
        "mandatory": 5
      },
      "confidence": 25
    },
    "scores": {
      "supply": 3.57,
      "demand": 3.57,
      "policy_strength": 29.29,
      "confidence": 25,
      "interpretations": {
        "supply": "Neutral supply impact",
        "demand": "Neutral demand impact",
        "policy_strength": "Encouraged/voluntary policy",
        "overall": "Low confidence: neutral price impact with voluntary measures"
      }
    },
    "timestamp": "2025-08-11T05:04:49.111736"
  },
  {
    "doc_id": "1c4184f7e11bca89",
    "title": "湖北省产品碳足迹公共服务平台正式发布",
    "source": "HBETS",
    "publish_date": "2014-02-24T00:00:00",
    "similarities": {
      "supply": {
        "major_decrease": 30,
        "minor_decrease": 25,
        "minor_increase": 20,
        "major_increase": 35
      },
      "demand": {
        "major_decrease": 30,
        "minor_decrease": 25,
        "minor_increase": 20,
        "major_increase": 35
      },
      "policy_strength": {
        "informational": 40,
        "encouraged": 60,
        "binding": 20,
        "mandatory": 15
      },
      "confidence": 50
    },
    "scores": {
      "supply": 2.27,
      "demand": 2.27,
      "policy_strength": 35.7,
      "confidence": 50,
      "interpretations": {
        "supply": "Neutral supply impact",
        "demand": "Neutral demand impact",
        "policy_strength": "Encouraged/voluntary policy",
        "overall": "Low confidence: neutral price impact with voluntary measures"
      }
    },
    "timestamp": "2025-08-11T05:04:49.214707"
  },
  {
    "doc_id": "86a3fadd34f6cdaa",
    "title": "MBAESG双驱商业领袖高级研修班招生简章",
    "source": "HBETS",
    "publish_date": "2014-01-07T00:00:00",
    "similarities": {
      "supply": {
        "major_decrease": 30,
        "minor_decrease": 20,
        "minor_increase": 25,
        "major_increase": 35
      },
      "demand": {
        "major_decrease": 30,
        "minor_decrease": 25,
        "minor_increase": 40,
        "major_increase": 35
      },
      "policy_strength": {
        "informational": 20,
        "encouraged": 50,
        "binding": 15,
        "mandatory": 10
      },
      "confidence": 40
    },
    "scores": {
      "supply": 6.82,
      "demand": 9.62,
      "policy_strength": 38.47,
      "confidence": 40,
      "interpretations": {
        "supply": "Neutral supply impact",
        "demand": "Neutral demand impact",
        "policy_strength": "Encouraged/voluntary policy",
        "overall": "Low confidence: neutral price impact with voluntary measures"
      }
    },
    "timestamp": "2025-08-11T05:04:49.329724"
  },
  {
    "doc_id": "b1244c8c52f279e5",
    "title": "校企合作湖北碳交获评全国水利与生态环保行业高校学生实习实践基地",
    "source": "HBETS",
    "publish_date": "2013-08-21T00:00:00",
    "similarities": {
      "supply": {
        "major_decrease": 20,
        "minor_decrease": 15,
        "minor_increase": 10,
        "major_increase": 25
      },
      "demand": {
        "major_decrease": 20,
        "minor_decrease": 15,
        "minor_increase": 10,
        "major_increase": 25
      },
      "policy_strength": {
        "informational": 30,
        "encouraged": 40,
        "binding": 10,
        "mandatory": 5
      },
      "confidence": 25
    },
    "scores": {
      "supply": 3.57,
      "demand": 3.57,
      "policy_strength": 29.29,
      "confidence": 25,
      "interpretations": {
        "supply": "Neutral supply impact",
        "demand": "Neutral demand impact",
        "policy_strength": "Encouraged/voluntary policy",
        "overall": "Low confidence: neutral price impact with voluntary measures"
      }
    },
    "timestamp": "2025-08-11T05:04:49.348245"
  },
  {
    "doc_id": "1810940ad4b81fe3",
    "title": "湖北省产品碳足迹公共服务平台正式发布",
    "source": "HBETS",
    "publish_date": "2013-12-23T00:00:00",
    "similarities": {
      "supply": {
        "major_decrease": 30,
        "minor_decrease": 25,
        "minor_increase": 20,
        "major_increase": 35
      },
      "demand": {
        "major_decrease": 30,
        "minor_decrease": 25,
        "minor_increase": 20,
        "major_increase": 35
      },
      "policy_strength": {
        "informational": 40,
        "encouraged": 70,
        "binding": 20,
        "mandatory": 15
      },
      "confidence": 55
    },
    "scores": {
      "supply": 2.27,
      "demand": 2.27,
      "policy_strength": 35.52,
      "confidence": 55,
      "interpretations": {
        "supply": "Neutral supply impact",
        "demand": "Neutral demand impact",
        "policy_strength": "Encouraged/voluntary policy",
        "overall": "Low confidence: neutral price impact with voluntary measures"
      }
    },
    "timestamp": "2025-08-11T05:04:49.452383"
  },
  {
    "doc_id": "4d4f8444bb38a64e",
    "title": "湖北省产品碳足迹公共服务平台正式发布",
    "source": "HBETS",
    "publish_date": "2014-02-28T00:00:00",
    "similarities": {
      "supply": {
        "major_decrease": 30,
        "minor_decrease": 25,
        "minor_increase": 20,
        "major_increase": 35
      },
      "demand": {
        "major_decrease": 30,
        "minor_decrease": 25,
        "minor_increase": 20,
        "major_increase": 35
      },
      "policy_strength": {
        "informational": 40,
        "encouraged": 70,
        "binding": 20,
        "mandatory": 15
      },
      "confidence": 50
    },
    "scores": {
      "supply": 2.27,
      "demand": 2.27,
      "policy_strength": 35.52,
      "confidence": 50,
      "interpretations": {
        "supply": "Neutral supply impact",
        "demand": "Neutral demand impact",
        "policy_strength": "Encouraged/voluntary policy",
        "overall": "Low confidence: neutral price impact with voluntary measures"
      }
    },
    "timestamp": "2025-08-11T05:04:49.648258"
  },
  {
    "doc_id": "5a1a127c9f0465b7",
    "title": "湖北碳交助力湖北省首家政策性银行实现碳中和",
    "source": "HBETS",
    "publish_date": "2014-01-24T00:00:00",
    "similarities": {
      "supply": {
        "major_decrease": 30,
        "minor_decrease": 20,
        "minor_increase": 25,
        "major_increase": 35
      },
      "demand": {
        "major_decrease": 30,
        "minor_decrease": 20,
        "minor_increase": 25,
        "major_increase": 35
      },
      "policy_strength": {
        "informational": 40,
        "encouraged": 60,
        "binding": 20,
        "mandatory": 10
      },
      "confidence": 50
    },
    "scores": {
      "supply": 6.82,
      "demand": 6.82,
      "policy_strength": 33.23,
      "confidence": 50,
      "interpretations": {
        "supply": "Neutral supply impact",
        "demand": "Neutral demand impact",
        "policy_strength": "Encouraged/voluntary policy",
        "overall": "Low confidence: neutral price impact with voluntary measures"
      }
    },
    "timestamp": "2025-08-11T05:04:49.660062"
  },
  {
    "doc_id": "9ba5eac388f1d435",
    "title": "广州碳排放权交易中心董事长张争鸣：碳市场扩围将有助于激发市场活力，赋能企业绿色转型",
    "source": "GZETS",
    "publish_date": "2025-04-01T00:00:00",
    "similarities": {
      "supply": {
        "major_decrease": 75,
        "minor_decrease": 60,
        "minor_increase": 50,
        "major_increase": 80
      },
      "demand": {
        "major_decrease": 75,
        "minor_decrease": 60,
        "minor_increase": 55,
        "major_increase": 80
      },
      "policy_strength": {
        "informational": 65,
        "encouraged": 70,
        "binding": 60,
        "mandatory": 55
      },
      "confidence": 75
    },
    "scores": {
      "supply": 0.0,
      "demand": 0.93,
      "policy_strength": 47.32,
      "confidence": 75,
      "interpretations": {
        "supply": "Neutral supply impact",
        "demand": "Neutral demand impact",
        "policy_strength": "Encouraged/voluntary policy",
        "overall": "Moderate confidence: neutral price impact with voluntary measures"
      }
    },
    "timestamp": "2025-08-11T05:04:49.680537"
  },
  {
    "doc_id": "de424408e2478d85",
    "title": "校企合作湖北碳交获评全国水利与生态环保行业高校学生实习实践基地",
    "source": "HBETS",
    "publish_date": "2013-04-01T00:00:00",
    "similarities": {
      "supply": {
        "major_decrease": 20,
        "minor_decrease": 15,
        "minor_increase": 10,
        "major_increase": 25
      },
      "demand": {
        "major_decrease": 20,
        "minor_decrease": 15,
        "minor_increase": 10,
        "major_increase": 25
      },
      "policy_strength": {
        "informational": 30,
        "encouraged": 35,
        "binding": 20,
        "mandatory": 15
      },
      "confidence": 25
    },
    "scores": {
      "supply": 3.57,
      "demand": 3.57,
      "policy_strength": 39.95,
      "confidence": 25,
      "interpretations": {
        "supply": "Neutral supply impact",
        "demand": "Neutral demand impact",
        "policy_strength": "Encouraged/voluntary policy",
        "overall": "Low confidence: neutral price impact with voluntary measures"
      }
    },
    "timestamp": "2025-08-11T05:04:49.707561"
  },
  {
    "doc_id": "f8e39922514ef78d",
    "title": "盘活碳资产：碳配额线上抵质押融资业务",
    "source": "GZETS",
    "publish_date": "2025-02-28T00:00:00",
    "similarities": {
      "supply": {
        "major_decrease": 60,
        "minor_decrease": 50,
        "minor_increase": 40,
        "major_increase": 70
      },
      "demand": {
        "major_decrease": 60,
        "minor_decrease": 50,
        "minor_increase": 40,
        "major_increase": 70
      },
      "policy_strength": {
        "informational": 30,
        "encouraged": 40,
        "binding": 50,
        "mandatory": 60
      },
      "confidence": 65
    },
    "scores": {
      "supply": 2.27,
      "demand": 2.27,
      "policy_strength": 59.28,
      "confidence": 65,
      "interpretations": {
        "supply": "Neutral supply impact",
        "demand": "Neutral demand impact",
        "policy_strength": "Binding guidance",
        "overall": "Moderate confidence: neutral price impact with binding guidance"
      }
    },
    "timestamp": "2025-08-11T05:04:49.723580"
  },
  {
    "doc_id": "0cf2a5848822b2c7",
    "title": "【邀请函】企业碳排放和碳足迹管理实践与应用主题沙龙活动",
    "source": "GZETS",
    "publish_date": "2024-10-31T00:00:00",
    "similarities": {
      "supply": {
        "major_decrease": 30,
        "minor_decrease": 20,
        "minor_increase": 25,
        "major_increase": 35
      },
      "demand": {
        "major_decrease": 30,
        "minor_decrease": 25,
        "minor_increase": 20,
        "major_increase": 40
      },
      "policy_strength": {
        "informational": 15,
        "encouraged": 25,
        "binding": 10,
        "mandatory": 20
      },
      "confidence": 25
    },
    "scores": {
      "supply": 6.82,
      "demand": 6.52,
      "policy_strength": 49.93,
      "confidence": 25,
      "interpretations": {
        "supply": "Neutral supply impact",
        "demand": "Neutral demand impact",
        "policy_strength": "Encouraged/voluntary policy",
        "overall": "Low confidence: neutral price impact with voluntary measures"
      }
    },
    "timestamp": "2025-08-11T05:04:49.810892"
  },
  {
    "doc_id": "7ff6e7af84220092",
    "title": "琴碳星人趣味徒步活动圆满举办！广州碳交中心助力低碳生活新风尚",
    "source": "GZETS",
    "publish_date": "2025-02-24T00:00:00",
    "similarities": {
      "supply": {
        "major_decrease": 10,
        "minor_decrease": 15,
        "minor_increase": 20,
        "major_increase": 25
      },
      "demand": {
        "major_decrease": 10,
        "minor_decrease": 15,
        "minor_increase": 30,
        "major_increase": 25
      },
      "policy_strength": {
        "informational": 20,
        "encouraged": 50,
        "binding": 10,
        "mandatory": 10
      },
      "confidence": 30
    },
    "scores": {
      "supply": 25.0,
      "demand": 28.12,
      "policy_strength": 36.89,
      "confidence": 30,
      "interpretations": {
        "supply": "Neutral supply impact",
        "demand": "Minor demand increase",
        "policy_strength": "Encouraged/voluntary policy",
        "overall": "Low confidence: neutral price impact with voluntary measures"
      }
    },
    "timestamp": "2025-08-11T05:04:49.827802"
  },
  {
    "doc_id": "0243abc01b9fa6ba",
    "title": "琴碳星人携手广州碳交中心助力低碳生活走入横琴粤澳深度合作区市民服务中心",
    "source": "GZETS",
    "publish_date": "2025-02-13T00:00:00",
    "similarities": {
      "supply": {
        "major_decrease": 20,
        "minor_decrease": 15,
        "minor_increase": 25,
        "major_increase": 30
      },
      "demand": {
        "major_decrease": 20,
        "minor_decrease": 15,
        "minor_increase": 30,
        "major_increase": 25
      },
      "policy_strength": {
        "informational": 40,
        "encouraged": 60,
        "binding": 10,
        "mandatory": 5
      },
      "confidence": 40
    },
    "scores": {
      "supply": 16.67,
      "demand": 13.89,
      "policy_strength": 27.39,
      "confidence": 40,
      "interpretations": {
        "supply": "Neutral supply impact",
        "demand": "Neutral demand impact",
        "policy_strength": "Encouraged/voluntary policy",
        "overall": "Low confidence: neutral price impact with voluntary measures"
      }
    },
    "timestamp": "2025-08-11T05:04:49.869146"
  },
  {
    "doc_id": "053f0889a9eaa7d2",
    "title": "绿美广东 金融赋能——广州碳交中心、上海清算所、华夏银行广州分行联合举办广东区域碳融资系列业务交流会",
    "source": "GZETS",
    "publish_date": "2025-04-30T00:00:00",
    "similarities": {
      "supply": {
        "major_decrease": 70,
        "minor_decrease": 60,
        "minor_increase": 50,
        "major_increase": 80
      },
      "demand": {
        "major_decrease": 70,
        "minor_decrease": 60,
        "minor_increase": 50,
        "major_increase": 80
      },
      "policy_strength": {
        "informational": 75,
        "encouraged": 65,
        "binding": 55,
        "mandatory": 50
      },
      "confidence": 75
    },
    "scores": {
      "supply": 1.92,
      "demand": 1.92,
      "policy_strength": 44.2,
      "confidence": 75,
      "interpretations": {
        "supply": "Neutral supply impact",
        "demand": "Neutral demand impact",
        "policy_strength": "Encouraged/voluntary policy",
        "overall": "Moderate confidence: neutral price impact with voluntary measures"
      }
    },
    "timestamp": "2025-08-11T05:04:49.883527"
  },
  {
    "doc_id": "9afb9d241cfd568c",
    "title": "广东省碳排放配额线上抵质押融资业务启动仪式成功举行",
    "source": "GZETS",
    "publish_date": "2024-12-05T00:00:00",
    "similarities": {
      "supply": {
        "major_decrease": 40,
        "minor_decrease": 30,
        "minor_increase": 20,
        "major_increase": 50
      },
      "demand": {
        "major_decrease": 40,
        "minor_decrease": 30,
        "minor_increase": 20,
        "major_increase": 50
      },
      "policy_strength": {
        "informational": 60,
        "encouraged": 70,
        "binding": 50,
        "mandatory": 40
      },
      "confidence": 60
    },
    "scores": {
      "supply": 3.57,
      "demand": 3.57,
      "policy_strength": 43.91,
      "confidence": 60,
      "interpretations": {
        "supply": "Neutral supply impact",
        "demand": "Neutral demand impact",
        "policy_strength": "Encouraged/voluntary policy",
        "overall": "Low confidence: neutral price impact with voluntary measures"
      }
    },
    "timestamp": "2025-08-11T05:04:49.898792"
  },
  {
    "doc_id": "a745e28f1f066f41",
    "title": "加入琴碳星人碳普惠平台，开启绿色商业新征程",
    "source": "GZETS",
    "publish_date": "2025-04-10T00:00:00",
    "similarities": {
      "supply": {
        "major_decrease": 20,
        "minor_decrease": 15,
        "minor_increase": 10,
        "major_increase": 25
      },
      "demand": {
        "major_decrease": 20,
        "minor_decrease": 15,
        "minor_increase": 30,
        "major_increase": 40
      },
      "policy_strength": {
        "informational": 25,
        "encouraged": 50,
        "binding": 10,
        "mandatory": 5
      },
      "confidence": 30
    },
    "scores": {
      "supply": 3.57,
      "demand": 26.19,
      "policy_strength": 31.33,
      "confidence": 30,
      "interpretations": {
        "supply": "Neutral supply impact",
        "demand": "Minor demand increase",
        "policy_strength": "Encouraged/voluntary policy",
        "overall": "Low confidence: neutral price impact with voluntary measures"
      }
    },
    "timestamp": "2025-08-11T05:04:49.996555"
  },
  {
    "doc_id": "52e11a05d5c7d6e4",
    "title": "关于举办温室气体管理师基础知识课程培训的通知",
    "source": "HBETS",
    "publish_date": "2013-11-28T00:00:00",
    "similarities": {
      "supply": {
        "major_decrease": 30,
        "minor_decrease": 20,
        "minor_increase": 25,
        "major_increase": 40
      },
      "demand": {
        "major_decrease": 30,
        "minor_decrease": 20,
        "minor_increase": 25,
        "major_increase": 40
      },
      "policy_strength": {
        "informational": 50,
        "encouraged": 60,
        "binding": 40,
        "mandatory": 30
      },
      "confidence": 50
    },
    "scores": {
      "supply": 10.87,
      "demand": 10.87,
      "policy_strength": 42.56,
      "confidence": 50,
      "interpretations": {
        "supply": "Neutral supply impact",
        "demand": "Neutral demand impact",
        "policy_strength": "Encouraged/voluntary policy",
        "overall": "Low confidence: neutral price impact with voluntary measures"
      }
    },
    "timestamp": "2025-08-11T05:04:50.044009"
  },
  {
    "doc_id": "02ddb087b1406eb4",
    "title": "相聚广州碳交中心 共研广东碳市场及碳金融发展",
    "source": "GZETS",
    "publish_date": "2025-02-20T00:00:00",
    "similarities": {
      "supply": {
        "major_decrease": 75,
        "minor_decrease": 60,
        "minor_increase": 50,
        "major_increase": 70
      },
      "demand": {
        "major_decrease": 75,
        "minor_decrease": 65,
        "minor_increase": 55,
        "major_increase": 80
      },
      "policy_strength": {
        "informational": 50,
        "encouraged": 65,
        "binding": 70,
        "mandatory": 80
      },
      "confidence": 70
    },
    "scores": {
      "supply": -3.92,
      "demand": 0.0,
      "policy_strength": 55.98,
      "confidence": 70,
      "interpretations": {
        "supply": "Neutral supply impact",
        "demand": "Neutral demand impact",
        "policy_strength": "Binding guidance",
        "overall": "Moderate confidence: neutral price impact with binding guidance"
      }
    },
    "timestamp": "2025-08-11T05:04:50.055516"
  },
  {
    "doc_id": "53623b69fb6ca5d2",
    "title": "转型金融助力经济高质量发展主题沙龙：广东工业企业低碳转型发展的机遇与挑战",
    "source": "GZETS",
    "publish_date": "2024-12-23T00:00:00",
    "similarities": {
      "supply": {
        "major_decrease": 40,
        "minor_decrease": 30,
        "minor_increase": 20,
        "major_increase": 50
      },
      "demand": {
        "major_decrease": 40,
        "minor_decrease": 30,
        "minor_increase": 20,
        "major_increase": 50
      },
      "policy_strength": {
        "informational": 60,
        "encouraged": 70,
        "binding": 50,
        "mandatory": 40
      },
      "confidence": 60
    },
    "scores": {
      "supply": 3.57,
      "demand": 3.57,
      "policy_strength": 43.91,
      "confidence": 60,
      "interpretations": {
        "supply": "Neutral supply impact",
        "demand": "Neutral demand impact",
        "policy_strength": "Encouraged/voluntary policy",
        "overall": "Low confidence: neutral price impact with voluntary measures"
      }
    },
    "timestamp": "2025-08-11T05:04:50.084209"
  },
  {
    "doc_id": "589d3ea032882ba3",
    "title": "倒计时1天  广州碳交中心承建的横琴粤澳深度合作区琴碳星人碳普惠小程序即将上线",
    "source": "GZETS",
    "publish_date": "2024-10-16T00:00:00",
    "similarities": {
      "supply": {
        "major_decrease": 20,
        "minor_decrease": 15,
        "minor_increase": 10,
        "major_increase": 25
      },
      "demand": {
        "major_decrease": 20,
        "minor_decrease": 15,
        "minor_increase": 30,
        "major_increase": 40
      },
      "policy_strength": {
        "informational": 10,
        "encouraged": 50,
        "binding": 5,
        "mandatory": 5
      },
      "confidence": 35
    },
    "scores": {
      "supply": 3.57,
      "demand": 26.19,
      "policy_strength": 35.5,
      "confidence": 35,
      "interpretations": {
        "supply": "Neutral supply impact",
        "demand": "Minor demand increase",
        "policy_strength": "Encouraged/voluntary policy",
        "overall": "Low confidence: neutral price impact with voluntary measures"
      }
    },
    "timestamp": "2025-08-11T05:04:50.086861"
  },
  {
    "doc_id": "0696d85fbe424502",
    "title": "广州碳交中心参编的《粤港澳大湾区会展碳中和实施指南》正式发布",
    "source": "GZETS",
    "publish_date": "2025-04-01T00:00:00",
    "similarities": {
      "supply": {
        "major_decrease": 30,
        "minor_decrease": 20,
        "minor_increase": 25,
        "major_increase": 35
      },
      "demand": {
        "major_decrease": 30,
        "minor_decrease": 20,
        "minor_increase": 25,
        "major_increase": 40
      },
      "policy_strength": {
        "informational": 50,
        "encouraged": 60,
        "binding": 30,
        "mandatory": 20
      },
      "confidence": 45
    },
    "scores": {
      "supply": 6.82,
      "demand": 10.87,
      "policy_strength": 37.44,
      "confidence": 45,
      "interpretations": {
        "supply": "Neutral supply impact",
        "demand": "Neutral demand impact",
        "policy_strength": "Encouraged/voluntary policy",
        "overall": "Low confidence: neutral price impact with voluntary measures"
      }
    },
    "timestamp": "2025-08-11T05:04:50.094872"
  },
  {
    "doc_id": "98184df6d41f93af",
    "title": "广州碳交中心生态产品价值实现平台再次落地海草床生态系统碳汇产品交易",
    "source": "GZETS",
    "publish_date": "2025-04-11T00:00:00",
    "similarities": {
      "supply": {
        "major_decrease": 30,
        "minor_decrease": 20,
        "minor_increase": 25,
        "major_increase": 35
      },
      "demand": {
        "major_decrease": 30,
        "minor_decrease": 20,
        "minor_increase": 25,
        "major_increase": 35
      },
      "policy_strength": {
        "informational": 40,
        "encouraged": 50,
        "binding": 30,
        "mandatory": 20
      },
      "confidence": 40
    },
    "scores": {
      "supply": 6.82,
      "demand": 6.82,
      "policy_strength": 40.43,
      "confidence": 40,
      "interpretations": {
        "supply": "Neutral supply impact",
        "demand": "Neutral demand impact",
        "policy_strength": "Encouraged/voluntary policy",
        "overall": "Low confidence: neutral price impact with voluntary measures"
      }
    },
    "timestamp": "2025-08-11T05:04:50.110102"
  },
  {
    "doc_id": "abc6c514e06925f9",
    "title": "倒计时1天——广州碳交中心承办的琴碳星人趣味徒步活动活力开启",
    "source": "GZETS",
    "publish_date": "2025-02-21T00:00:00",
    "similarities": {
      "supply": {
        "major_decrease": 0,
        "minor_decrease": 0,
        "minor_increase": 0,
        "major_increase": 0
      },
      "demand": {
        "major_decrease": 0,
        "minor_decrease": 0,
        "minor_increase": 0,
        "major_increase": 0
      },
      "policy_strength": {
        "informational": 0,
        "encouraged": 0,
        "binding": 0,
        "mandatory": 0
      },
      "confidence": 0
    },
    "scores": {
      "supply": 0,
      "demand": 0,
      "policy_strength": 0,
      "confidence": 0,
      "interpretations": {
        "supply": "Neutral supply impact",
        "demand": "Neutral demand impact",
        "policy_strength": "Informational policy",
        "overall": "Low confidence: neutral price impact as informational guidance"
      }
    },
    "timestamp": "2025-08-11T05:04:50.275683"
  },
  {
    "doc_id": "5c53bf1495e3c7c4",
    "title": "广州碳交中心参与撰写的《香港绿色科技生态：融资机遇》报告正式发布",
    "source": "GZETS",
    "publish_date": "2025-02-05T00:00:00",
    "similarities": {
      "supply": {
        "major_decrease": 20,
        "minor_decrease": 15,
        "minor_increase": 25,
        "major_increase": 30
      },
      "demand": {
        "major_decrease": 20,
        "minor_decrease": 15,
        "minor_increase": 25,
        "major_increase": 30
      },
      "policy_strength": {
        "informational": 10,
        "encouraged": 15,
        "binding": 5,
        "mandatory": 5
      },
      "confidence": 25
    },
    "scores": {
      "supply": 16.67,
      "demand": 16.67,
      "policy_strength": 38.0,
      "confidence": 25,
      "interpretations": {
        "supply": "Neutral supply impact",
        "demand": "Neutral demand impact",
        "policy_strength": "Encouraged/voluntary policy",
        "overall": "Low confidence: neutral price impact with voluntary measures"
      }
    },
    "timestamp": "2025-08-11T05:04:50.292211"
  },
  {
    "doc_id": "8b13f48d792d20dc",
    "title": "湖北省产品碳足迹公共服务平台正式发布",
    "source": "HBETS",
    "publish_date": "2013-09-13T00:00:00",
    "similarities": {
      "supply": {
        "major_decrease": 20,
        "minor_decrease": 15,
        "minor_increase": 10,
        "major_increase": 25
      },
      "demand": {
        "major_decrease": 20,
        "minor_decrease": 15,
        "minor_increase": 30,
        "major_increase": 25
      },
      "policy_strength": {
        "informational": 30,
        "encouraged": 70,
        "binding": 10,
        "mandatory": 5
      },
      "confidence": 40
    },
    "scores": {
      "supply": 3.57,
      "demand": 13.89,
      "policy_strength": 30.26,
      "confidence": 40,
      "interpretations": {
        "supply": "Neutral supply impact",
        "demand": "Neutral demand impact",
        "policy_strength": "Encouraged/voluntary policy",
        "overall": "Low confidence: neutral price impact with voluntary measures"
      }
    },
    "timestamp": "2025-08-11T05:04:50.299742"
  },
  {
    "doc_id": "4e387403fdba37ed",
    "title": "广州碳交中心承办双碳战略 绿色转型 国企先行绿色低碳高质量发展活动",
    "source": "GZETS",
    "publish_date": "2024-11-19T00:00:00",
    "similarities": {
      "supply": {
        "major_decrease": 40,
        "minor_decrease": 30,
        "minor_increase": 20,
        "major_increase": 50
      },
      "demand": {
        "major_decrease": 40,
        "minor_decrease": 30,
        "minor_increase": 25,
        "major_increase": 55
      },
      "policy_strength": {
        "informational": 35,
        "encouraged": 50,
        "binding": 20,
        "mandatory": 15
      },
      "confidence": 45
    },
    "scores": {
      "supply": 3.57,
      "demand": 8.33,
      "policy_strength": 37.42,
      "confidence": 45,
      "interpretations": {
        "supply": "Neutral supply impact",
        "demand": "Neutral demand impact",
        "policy_strength": "Encouraged/voluntary policy",
        "overall": "Low confidence: neutral price impact with voluntary measures"
      }
    },
    "timestamp": "2025-08-11T05:04:50.337164"
  },
  {
    "doc_id": "c50b9222980591bc",
    "title": "琴碳星人横琴自然周、澳门绿化周  玩转低碳生活，解锁绿色未来！",
    "source": "GZETS",
    "publish_date": "2025-03-19T00:00:00",
    "similarities": {
      "supply": {
        "major_decrease": 10,
        "minor_decrease": 15,
        "minor_increase": 20,
        "major_increase": 25
      },
      "demand": {
        "major_decrease": 10,
        "minor_decrease": 15,
        "minor_increase": 30,
        "major_increase": 35
      },
      "policy_strength": {
        "informational": 5,
        "encouraged": 50,
        "binding": 0,
        "mandatory": 0
      },
      "confidence": 20
    },
    "scores": {
      "supply": 25.0,
      "demand": 36.11,
      "policy_strength": 30.0,
      "confidence": 20,
      "interpretations": {
        "supply": "Neutral supply impact",
        "demand": "Minor demand increase",
        "policy_strength": "Encouraged/voluntary policy",
        "overall": "Low confidence: neutral price impact with voluntary measures"
      }
    },
    "timestamp": "2025-08-11T05:04:50.609301"
  },
  {
    "doc_id": "a0a8f2741a507068",
    "title": "广东省2024年度碳排放配额分配方案解读",
    "source": "GZETS",
    "publish_date": "2025-05-12T00:00:00",
    "similarities": {
      "supply": {
        "major_decrease": 90,
        "minor_decrease": 60,
        "minor_increase": 30,
        "major_increase": 20
      },
      "demand": {
        "major_decrease": 90,
        "minor_decrease": 60,
        "minor_increase": 30,
        "major_increase": 20
      },
      "policy_strength": {
        "informational": 40,
        "encouraged": 25,
        "binding": 50,
        "mandatory": 70
      },
      "confidence": 75
    },
    "scores": {
      "supply": -42.5,
      "demand": -42.5,
      "policy_strength": 60.41,
      "confidence": 75,
      "interpretations": {
        "supply": "Minor supply decrease",
        "demand": "Minor demand decrease",
        "policy_strength": "Binding guidance",
        "overall": "Moderate confidence: neutral price impact with binding guidance"
      }
    },
    "timestamp": "2025-08-11T05:04:50.725500"
  },
  {
    "doc_id": "1c98ee96991e778a",
    "title": "广州碳排放权交易中心携手恒丰银行广州分行成功举办绿色金融沙龙活动",
    "source": "GZETS",
    "publish_date": "2024-11-13T00:00:00",
    "similarities": {
      "supply": {
        "major_decrease": 30,
        "minor_decrease": 20,
        "minor_increase": 25,
        "major_increase": 35
      },
      "demand": {
        "major_decrease": 30,
        "minor_decrease": 25,
        "minor_increase": 40,
        "major_increase": 35
      },
      "policy_strength": {
        "informational": 20,
        "encouraged": 50,
        "binding": 15,
        "mandatory": 10
      },
      "confidence": 40
    },
    "scores": {
      "supply": 6.82,
      "demand": 9.62,
      "policy_strength": 38.47,
      "confidence": 40,
      "interpretations": {
        "supply": "Neutral supply impact",
        "demand": "Neutral demand impact",
        "policy_strength": "Encouraged/voluntary policy",
        "overall": "Low confidence: neutral price impact with voluntary measures"
      }
    },
    "timestamp": "2025-08-11T05:04:51.775903"
  },
  {
    "doc_id": "faa8c93a061f3ea6",
    "title": "广东省碳排放管理和交易新纳入行业企业专题培训顺利举行",
    "source": "GZETS",
    "publish_date": "2024-03-29T00:00:00",
    "similarities": {
      "supply": {
        "major_decrease": 60,
        "minor_decrease": 50,
        "minor_increase": 40,
        "major_increase": 70
      },
      "demand": {
        "major_decrease": 60,
        "minor_decrease": 50,
        "minor_increase": 40,
        "major_increase": 70
      },
      "policy_strength": {
        "informational": 30,
        "encouraged": 40,
        "binding": 50,
        "mandatory": 60
      },
      "confidence": 55
    },
    "scores": {
      "supply": 2.27,
      "demand": 2.27,
      "policy_strength": 59.28,
      "confidence": 55,
      "interpretations": {
        "supply": "Neutral supply impact",
        "demand": "Neutral demand impact",
        "policy_strength": "Binding guidance",
        "overall": "Low confidence: neutral price impact with binding guidance"
      }
    },
    "timestamp": "2025-08-11T05:04:52.295561"
  },
  {
    "doc_id": "ea1c742658f0a3c1",
    "title": "第34个全国节能宣传周启动，广州碳交中心助力实现启动仪式碳中和",
    "source": "GZETS",
    "publish_date": "2024-05-15T00:00:00",
    "similarities": {
      "supply": {
        "major_decrease": 30,
        "minor_decrease": 25,
        "minor_increase": 20,
        "major_increase": 35
      },
      "demand": {
        "major_decrease": 30,
        "minor_decrease": 25,
        "minor_increase": 40,
        "major_increase": 45
      },
      "policy_strength": {
        "informational": 20,
        "encouraged": 35,
        "binding": 25,
        "mandatory": 30
      },
      "confidence": 40
    },
    "scores": {
      "supply": 2.27,
      "demand": 16.07,
      "policy_strength": 53.0,
      "confidence": 40,
      "interpretations": {
        "supply": "Neutral supply impact",
        "demand": "Neutral demand impact",
        "policy_strength": "Binding guidance",
        "overall": "Low confidence: neutral price impact with binding guidance"
      }
    },
    "timestamp": "2025-08-11T05:04:52.415289"
  },
  {
    "doc_id": "8f8e654d67467b0a",
    "title": "为经济社会发展全面绿色转型增添金融动力——2024年广东绿色金融改革创新推进会成功举办",
    "source": "GZETS",
    "publish_date": "2024-12-02T00:00:00",
    "similarities": {
      "supply": {
        "major_decrease": 30,
        "minor_decrease": 25,
        "minor_increase": 20,
        "major_increase": 35
      },
      "demand": {
        "major_decrease": 30,
        "minor_decrease": 25,
        "minor_increase": 40,
        "major_increase": 35
      },
      "policy_strength": {
        "informational": 50,
        "encouraged": 55,
        "binding": 20,
        "mandatory": 15
      },
      "confidence": 40
    },
    "scores": {
      "supply": 2.27,
      "demand": 9.62,
      "policy_strength": 33.25,
      "confidence": 40,
      "interpretations": {
        "supply": "Neutral supply impact",
        "demand": "Neutral demand impact",
        "policy_strength": "Encouraged/voluntary policy",
        "overall": "Low confidence: neutral price impact with voluntary measures"
      }
    },
    "timestamp": "2025-08-11T05:04:52.423173"
  },
  {
    "doc_id": "57471b3e7fd4b71d",
    "title": "广州碳交中心联合广东碳中和研究院（韶关）举办11月沙龙活动",
    "source": "GZETS",
    "publish_date": "2024-11-15T00:00:00",
    "similarities": {
      "supply": {
        "major_decrease": 40,
        "minor_decrease": 30,
        "minor_increase": 20,
        "major_increase": 50
      },
      "demand": {
        "major_decrease": 40,
        "minor_decrease": 30,
        "minor_increase": 20,
        "major_increase": 50
      },
      "policy_strength": {
        "informational": 20,
        "encouraged": 30,
        "binding": 40,
        "mandatory": 50
      },
      "confidence": 40
    },
    "scores": {
      "supply": 3.57,
      "demand": 3.57,
      "policy_strength": 61.93,
      "confidence": 40,
      "interpretations": {
        "supply": "Neutral supply impact",
        "demand": "Neutral demand impact",
        "policy_strength": "Binding guidance",
        "overall": "Low confidence: neutral price impact with binding guidance"
      }
    },
    "timestamp": "2025-08-11T05:04:52.439410"
  },
  {
    "doc_id": "a8b1494daa969375",
    "title": "广州碳交中心东莞碳市场服务中心正式成立",
    "source": "GZETS",
    "publish_date": "2024-07-17T00:00:00",
    "similarities": {
      "supply": {
        "major_decrease": 40,
        "minor_decrease": 30,
        "minor_increase": 20,
        "major_increase": 50
      },
      "demand": {
        "major_decrease": 40,
        "minor_decrease": 30,
        "minor_increase": 20,
        "major_increase": 50
      },
      "policy_strength": {
        "informational": 20,
        "encouraged": 30,
        "binding": 40,
        "mandatory": 50
      },
      "confidence": 45
    },
    "scores": {
      "supply": 3.57,
      "demand": 3.57,
      "policy_strength": 61.93,
      "confidence": 45,
      "interpretations": {
        "supply": "Neutral supply impact",
        "demand": "Neutral demand impact",
        "policy_strength": "Binding guidance",
        "overall": "Low confidence: neutral price impact with binding guidance"
      }
    },
    "timestamp": "2025-08-11T05:04:52.441480"
  },
  {
    "doc_id": "b21ca22a16293478",
    "title": "广州市社会主义学院与广州碳交中心联合打造党外干部培训新平台",
    "source": "GZETS",
    "publish_date": "2024-11-08T00:00:00",
    "similarities": {
      "supply": {
        "major_decrease": 20,
        "minor_decrease": 15,
        "minor_increase": 10,
        "major_increase": 25
      },
      "demand": {
        "major_decrease": 20,
        "minor_decrease": 15,
        "minor_increase": 10,
        "major_increase": 25
      },
      "policy_strength": {
        "informational": 30,
        "encouraged": 35,
        "binding": 20,
        "mandatory": 25
      },
      "confidence": 30
    },
    "scores": {
      "supply": 3.57,
      "demand": 3.57,
      "policy_strength": 45.41,
      "confidence": 30,
      "interpretations": {
        "supply": "Neutral supply impact",
        "demand": "Neutral demand impact",
        "policy_strength": "Encouraged/voluntary policy",
        "overall": "Low confidence: neutral price impact with voluntary measures"
      }
    },
    "timestamp": "2025-08-11T05:04:52.679710"
  },
  {
    "doc_id": "7320ebffe00badc6",
    "title": "广州碳交中心与毕马威中国签署战略合作协议，共同探索绿色低碳与生物多样性发展机遇",
    "source": "GZETS",
    "publish_date": "2024-04-19T00:00:00",
    "similarities": {
      "supply": {
        "major_decrease": 30,
        "minor_decrease": 25,
        "minor_increase": 20,
        "major_increase": 35
      },
      "demand": {
        "major_decrease": 30,
        "minor_decrease": 25,
        "minor_increase": 20,
        "major_increase": 35
      },
      "policy_strength": {
        "informational": 40,
        "encouraged": 50,
        "binding": 30,
        "mandatory": 25
      },
      "confidence": 40
    },
    "scores": {
      "supply": 2.27,
      "demand": 2.27,
      "policy_strength": 42.48,
      "confidence": 40,
      "interpretations": {
        "supply": "Neutral supply impact",
        "demand": "Neutral demand impact",
        "policy_strength": "Encouraged/voluntary policy",
        "overall": "Low confidence: neutral price impact with voluntary measures"
      }
    },
    "timestamp": "2025-08-11T05:04:52.734971"
  },
  {
    "doc_id": "5c274925f6c68c22",
    "title": "广州碳交中心承建碳普惠小程序\"琴碳星人\"正式上线",
    "source": "GZETS",
    "publish_date": "2024-10-18T00:00:00",
    "similarities": {
      "supply": {
        "major_decrease": 10,
        "minor_decrease": 15,
        "minor_increase": 20,
        "major_increase": 25
      },
      "demand": {
        "major_decrease": 10,
        "minor_decrease": 15,
        "minor_increase": 30,
        "major_increase": 40
      },
      "policy_strength": {
        "informational": 5,
        "encouraged": 70,
        "binding": 0,
        "mandatory": 0
      },
      "confidence": 30
    },
    "scores": {
      "supply": 25.0,
      "demand": 39.47,
      "policy_strength": 30.8,
      "confidence": 30,
      "interpretations": {
        "supply": "Neutral supply impact",
        "demand": "Minor demand increase",
        "policy_strength": "Encouraged/voluntary policy",
        "overall": "Low confidence: neutral price impact with voluntary measures"
      }
    },
    "timestamp": "2025-08-11T05:04:52.737976"
  },
  {
    "doc_id": "ab178456b7f57efc",
    "title": "6月培训课堂精彩回顾，碳金融、ESG火花齐迸发",
    "source": "GZETS",
    "publish_date": "2024-07-05T00:00:00",
    "similarities": {
      "supply": {
        "major_decrease": 60,
        "minor_decrease": 50,
        "minor_increase": 40,
        "major_increase": 70
      },
      "demand": {
        "major_decrease": 60,
        "minor_decrease": 50,
        "minor_increase": 40,
        "major_increase": 70
      },
      "policy_strength": {
        "informational": 30,
        "encouraged": 50,
        "binding": 60,
        "mandatory": 70
      },
      "confidence": 65
    },
    "scores": {
      "supply": 2.27,
      "demand": 2.27,
      "policy_strength": 60.33,
      "confidence": 65,
      "interpretations": {
        "supply": "Neutral supply impact",
        "demand": "Neutral demand impact",
        "policy_strength": "Binding guidance",
        "overall": "Moderate confidence: neutral price impact with binding guidance"
      }
    },
    "timestamp": "2025-08-11T05:04:52.784804"
  },
  {
    "doc_id": "d8543a03ff5da08f",
    "title": "广州碳交中心成功举办《海草床生态修复碳汇计量与监测方法》专题评审会",
    "source": "GZETS",
    "publish_date": "2024-04-30T00:00:00",
    "similarities": {
      "supply": {
        "major_decrease": 20,
        "minor_decrease": 15,
        "minor_increase": 10,
        "major_increase": 25
      },
      "demand": {
        "major_decrease": 20,
        "minor_decrease": 15,
        "minor_increase": 10,
        "major_increase": 25
      },
      "policy_strength": {
        "informational": 30,
        "encouraged": 25,
        "binding": 20,
        "mandatory": 20
      },
      "confidence": 25
    },
    "scores": {
      "supply": 3.57,
      "demand": 3.57,
      "policy_strength": 43.84,
      "confidence": 25,
      "interpretations": {
        "supply": "Neutral supply impact",
        "demand": "Neutral demand impact",
        "policy_strength": "Encouraged/voluntary policy",
        "overall": "Low confidence: neutral price impact with voluntary measures"
      }
    },
    "timestamp": "2025-08-11T05:04:52.808394"
  },
  {
    "doc_id": "1da24e824a0d8d82",
    "title": "深化专业素养，提升实操技能——广州碳交中心成功举办合规培训",
    "source": "GZETS",
    "publish_date": "2024-07-04T00:00:00",
    "similarities": {
      "supply": {
        "major_decrease": 30,
        "minor_decrease": 20,
        "minor_increase": 25,
        "major_increase": 40
      },
      "demand": {
        "major_decrease": 30,
        "minor_decrease": 25,
        "minor_increase": 20,
        "major_increase": 35
      },
      "policy_strength": {
        "informational": 15,
        "encouraged": 20,
        "binding": 10,
        "mandatory": 5
      },
      "confidence": 25
    },
    "scores": {
      "supply": 10.87,
      "demand": 2.27,
      "policy_strength": 36.6,
      "confidence": 25,
      "interpretations": {
        "supply": "Neutral supply impact",
        "demand": "Neutral demand impact",
        "policy_strength": "Encouraged/voluntary policy",
        "overall": "Low confidence: neutral price impact with voluntary measures"
      }
    },
    "timestamp": "2025-08-11T05:04:52.860756"
  },
  {
    "doc_id": "9373bff82658b880",
    "title": "广州碳交中心举办广东碳配额资产证券化业务研讨会",
    "source": "GZETS",
    "publish_date": "2024-05-30T00:00:00",
    "similarities": {
      "supply": {
        "major_decrease": 60,
        "minor_decrease": 50,
        "minor_increase": 40,
        "major_increase": 70
      },
      "demand": {
        "major_decrease": 60,
        "minor_decrease": 50,
        "minor_increase": 40,
        "major_increase": 70
      },
      "policy_strength": {
        "informational": 50,
        "encouraged": 60,
        "binding": 70,
        "mandatory": 80
      },
      "confidence": 65
    },
    "scores": {
      "supply": 2.27,
      "demand": 2.27,
      "policy_strength": 56.42,
      "confidence": 65,
      "interpretations": {
        "supply": "Neutral supply impact",
        "demand": "Neutral demand impact",
        "policy_strength": "Binding guidance",
        "overall": "Moderate confidence: neutral price impact with binding guidance"
      }
    },
    "timestamp": "2025-08-11T05:04:52.914853"
  },
  {
    "doc_id": "80144224c04b92b8",
    "title": "广州市事业单位干部培训现场教学基地落地广州碳交中心",
    "source": "GZETS",
    "publish_date": "2024-05-14T00:00:00",
    "similarities": {
      "supply": {
        "major_decrease": 20,
        "minor_decrease": 15,
        "minor_increase": 10,
        "major_increase": 25
      },
      "demand": {
        "major_decrease": 20,
        "minor_decrease": 15,
        "minor_increase": 10,
        "major_increase": 25
      },
      "policy_strength": {
        "informational": 30,
        "encouraged": 25,
        "binding": 20,
        "mandatory": 15
      },
      "confidence": 20
    },
    "scores": {
      "supply": 3.57,
      "demand": 3.57,
      "policy_strength": 40.72,
      "confidence": 20,
      "interpretations": {
        "supply": "Neutral supply impact",
        "demand": "Neutral demand impact",
        "policy_strength": "Encouraged/voluntary policy",
        "overall": "Low confidence: neutral price impact with voluntary measures"
      }
    },
    "timestamp": "2025-08-11T05:04:53.005100"
  },
  {
    "doc_id": "43b08a91d214ede7",
    "title": "碳市场建设的问题与发展路径——基于构建碳人民币体系视角",
    "source": "GZETS",
    "publish_date": "2024-04-18T00:00:00",
    "similarities": {
      "supply": {
        "major_decrease": 60,
        "minor_decrease": 50,
        "minor_increase": 40,
        "major_increase": 70
      },
      "demand": {
        "major_decrease": 60,
        "minor_decrease": 50,
        "minor_increase": 55,
        "major_increase": 75
      },
      "policy_strength": {
        "informational": 65,
        "encouraged": 70,
        "binding": 60,
        "mandatory": 55
      },
      "confidence": 65
    },
    "scores": {
      "supply": 2.27,
      "demand": 7.29,
      "policy_strength": 47.32,
      "confidence": 65,
      "interpretations": {
        "supply": "Neutral supply impact",
        "demand": "Neutral demand impact",
        "policy_strength": "Encouraged/voluntary policy",
        "overall": "Moderate confidence: neutral price impact with voluntary measures"
      }
    },
    "timestamp": "2025-08-11T05:04:53.078757"
  },
  {
    "doc_id": "4613d5696d729928",
    "title": "全国首单海草床生态系统碳汇产品在广州碳交中心生态产品价值实现平台落地",
    "source": "GZETS",
    "publish_date": "2024-06-14T00:00:00",
    "similarities": {
      "supply": {
        "major_decrease": 20,
        "minor_decrease": 15,
        "minor_increase": 10,
        "major_increase": 25
      },
      "demand": {
        "major_decrease": 20,
        "minor_decrease": 15,
        "minor_increase": 10,
        "major_increase": 30
      },
      "policy_strength": {
        "informational": 25,
        "encouraged": 35,
        "binding": 20,
        "mandatory": 15
      },
      "confidence": 60
    },
    "scores": {
      "supply": 3.57,
      "demand": 10.0,
      "policy_strength": 42.05,
      "confidence": 60,
      "interpretations": {
        "supply": "Neutral supply impact",
        "demand": "Neutral demand impact",
        "policy_strength": "Encouraged/voluntary policy",
        "overall": "Low confidence: neutral price impact with voluntary measures"
      }
    },
    "timestamp": "2025-08-11T05:04:53.120673"
  },
  {
    "doc_id": "63decbe5f24d5073",
    "title": "广州碳排放权交易中心联合江门双碳实验室成功举办8月会员沙龙活动",
    "source": "GZETS",
    "publish_date": "2024-08-27T00:00:00",
    "similarities": {
      "supply": {
        "major_decrease": 30,
        "minor_decrease": 20,
        "minor_increase": 25,
        "major_increase": 35
      },
      "demand": {
        "major_decrease": 30,
        "minor_decrease": 25,
        "minor_increase": 40,
        "major_increase": 35
      },
      "policy_strength": {
        "informational": 20,
        "encouraged": 25,
        "binding": 30,
        "mandatory": 30
      },
      "confidence": 30
    },
    "scores": {
      "supply": 6.82,
      "demand": 9.62,
      "policy_strength": 55.57,
      "confidence": 30,
      "interpretations": {
        "supply": "Neutral supply impact",
        "demand": "Neutral demand impact",
        "policy_strength": "Binding guidance",
        "overall": "Low confidence: neutral price impact with binding guidance"
      }
    },
    "timestamp": "2025-08-11T05:04:53.526020"
  },
  {
    "doc_id": "525f9439d3460ea0",
    "title": "2023年度广东碳市场新增控排企业履约指引专题沙龙活动成功举办",
    "source": "GZETS",
    "publish_date": "2024-07-06T00:00:00",
    "similarities": {
      "supply": {
        "major_decrease": 40,
        "minor_decrease": 60,
        "minor_increase": 50,
        "major_increase": 70
      },
      "demand": {
        "major_decrease": 40,
        "minor_decrease": 70,
        "minor_increase": 50,
        "major_increase": 60
      },
      "policy_strength": {
        "informational": 30,
        "encouraged": 50,
        "binding": 70,
        "mandatory": 80
      },
      "confidence": 65
    },
    "scores": {
      "supply": 11.36,
      "demand": 4.55,
      "policy_strength": 62.35,
      "confidence": 65,
      "interpretations": {
        "supply": "Neutral supply impact",
        "demand": "Neutral demand impact",
        "policy_strength": "Binding guidance",
        "overall": "Moderate confidence: neutral price impact with binding guidance"
      }
    },
    "timestamp": "2025-08-11T05:04:53.676146"
  },
  {
    "doc_id": "dd19bfc68e97001e",
    "title": "广州碳排放权交易中心成功举办广东碳市场投资机构座谈会",
    "source": "GZETS",
    "publish_date": "2024-10-23T00:00:00",
    "similarities": {
      "supply": {
        "major_decrease": 60,
        "minor_decrease": 70,
        "minor_increase": 50,
        "major_increase": 80
      },
      "demand": {
        "major_decrease": 60,
        "minor_decrease": 70,
        "minor_increase": 50,
        "major_increase": 80
      },
      "policy_strength": {
        "informational": 40,
        "encouraged": 50,
        "binding": 70,
        "mandatory": 60
      },
      "confidence": 65
    },
    "scores": {
      "supply": 3.85,
      "demand": 3.85,
      "policy_strength": 56.09,
      "confidence": 65,
      "interpretations": {
        "supply": "Neutral supply impact",
        "demand": "Neutral demand impact",
        "policy_strength": "Binding guidance",
        "overall": "Moderate confidence: neutral price impact with binding guidance"
      }
    },
    "timestamp": "2025-08-11T05:04:54.005322"
  },
  {
    "doc_id": "ed28871663a486b1",
    "title": "生态环境部环境规划院—行赴广州碳交中心调研交流",
    "source": "GZETS",
    "publish_date": "2024-06-11T00:00:00",
    "similarities": {
      "supply": {
        "major_decrease": 70,
        "minor_decrease": 60,
        "minor_increase": 50,
        "major_increase": 65
      },
      "demand": {
        "major_decrease": 70,
        "minor_decrease": 65,
        "minor_increase": 55,
        "major_increase": 60
      },
      "policy_strength": {
        "informational": 50,
        "encouraged": 55,
        "binding": 60,
        "mandatory": 65
      },
      "confidence": 65
    },
    "scores": {
      "supply": -4.08,
      "demand": -6.0,
      "policy_strength": 53.63,
      "confidence": 65,
      "interpretations": {
        "supply": "Neutral supply impact",
        "demand": "Neutral demand impact",
        "policy_strength": "Binding guidance",
        "overall": "Moderate confidence: neutral price impact with binding guidance"
      }
    },
    "timestamp": "2025-08-11T05:04:58.711482"
  }
]