{
  "doc_id": "160d4225d8bd26da",
  "url": "https://www.cnemission.com/article/news/jysgg/202407/20240700003335.shtml",
  "title": "广州碳排权交易中心有限公司2024年公开招聘工作人员拟录用人选公示",
  "content": "按照上级招聘要求以及《广州碳排权交易中心有限公司招聘公告》规定，经报名、资格审査、测评、背调、体检等程序，我公司拟录取刘子扬、纪楚宁2名同志为工作人员（以上人员名单按姓氏笔画排序）。公示时间从2024年7月24日至2024年7月26日止，共3个工作日。公示期间，如对上述拟录用人员有异议请以书面形式（包括必要的证明材料）向广州碳排放权交易中心有限公司党群与综合管理部反映。反映情况必须使用真实姓名和联系方式，匿名信函将不予受理。联系人：党群与综合管理部 邵女士联系",
  "section": "Trading_Announcements",
  "publish_date": "2024-07-24T00:00:00",
  "view_count": null,
  "content_length": 232,
  "content_hash": "772f78b0c33aa50c3be71da402b64dff",
  "scraped_at": "2025-08-09T07:59:46.311195",
  "source": "GZETS",
  "source_detail": "广州碳排权交易中心",
  "source_name_cn": "广州碳排放权交易中心",
  "source_name_en": "Guangzhou Emission Trading Scheme"
}