{
  "doc_id": "b1737605c8e648fb",
  "url": "https://www.cnemission.com/article/news/jysgg/202408/20240800003351.shtml",
  "title": "【邀请函】碳管理与双碳创新技术会员沙龙",
  "content": "[Limited text content available]",
  "section": "Trading_Announcements",
  "publish_date": "2024-08-14T00:00:00",
  "view_count": null,
  "content_length": 32,
  "content_hash": "d84117566097227e0565440d1f4142d4",
  "scraped_at": "2025-08-09T07:59:44.891000",
  "source": "GZETS",
  "source_detail": "广州碳排放权交易中心",
  "source_name_cn": "广州碳排放权交易中心",
  "source_name_en": "Guangzhou Emission Trading Scheme"
}