{
  "doc_id": "ca4217328506b8e2",
  "url": "https://www.cnemission.com/article/news/jysgg/201609/20160900001167.shtml",
  "title": "关于2016年国庆节休市安排的公告",
  "content": "关于2016年国庆节休市安排的公告 尊敬的各交易参与人： 根据《国务院办公厅关于2016年部分节假日安排的通知》（国办发明电201518号），结合广东省实际情况，现将本所2016年国庆节休市安排公告如下 10月1日（星期六）至10月7日（星期五）休市，10月8日（星期六）和10月9日（星期日）为周末休市，10月10日（星期一）起照常开市。 特此公告。 广州碳排放权交易所 2016年9月28日",
  "section": "Trading_Announcements",
  "publish_date": "2016-09-28T00:00:00",
  "view_count": null,
  "content_length": 197,
  "content_hash": "c2525d741da95aa3e3efe3a375a631fe",
  "scraped_at": "2025-08-09T08:00:08.535628",
  "source": "GZETS",
  "source_detail": "广州碳排放权交易所",
  "source_name_cn": "广州碳排放权交易中心",
  "source_name_en": "Guangzhou Emission Trading Scheme"
}